{
"rip": 5,
"it": 5,
"up": 5,
"and": 11,
"start": 5,
"again": 5,
"books": 4,
"to": 10,
"scrape": 2,
"sandbox": 1,
"we": 1,
"love": 1,
"being": 1,
"scraped": 1,
"home": 1,
"music": 2,
"â": 10,
"35": 3,
"02": 3,
"in": 9,
"stock": 8,
"19": 2,
"available": 2,
"warning": 1,
"this": 1,
"is": 3,
"a": 6,
"demo": 1,
"website": 1,
"for": 2,
"web": 1,
"scraping": 1,
"purposes": 1,
"prices": 1,
"ratings": 1,
"here": 1,
"were": 4,
"randomly": 1,
"assigned": 1,
"have": 1,
"no": 1,
"real": 1,
"meaning": 1,
"product": 3,
"description": 1,
"punk": 8,
"s": 6,
"raw": 2,
"power": 2,
"rejuvenated": 2,
"rock": 2,
"but": 2,
"by": 2,
"the": 13,
"summer": 2,
"of": 7,
"1977": 2,
"movement": 2,
"had": 2,
"become": 2,
"parody": 2,
"itself": 2,
"celebration": 2,
"what": 2,
"happened": 2,
"next": 2,
"post": 4,
"bands": 2,
"like": 2,
"pil": 2,
"joy": 2,
"division": 2,
"talking": 2,
"heads": 2,
"fall": 2,
"human": 2,
"league": 2,
"dedicated": 2,
"themselves": 2,
"fulfilling": 2,
"unfinished": 2,
"musical": 2,
"revolution": 2,
"groups": 2,
"fervent": 2,
"modernists": 2,
"w": 1,
"whether": 1,
"experimenting": 1,
"with": 1,
"electronics": 1,
"machine": 1,
"rhythm": 1,
"or": 1,
"adapting": 1,
"ideas": 1,
"from": 1,
"dub": 1,
"reggae": 1,
"disco": 1,
"they": 2,
"totally": 1,
"confident": 1,
"could": 1,
"invent": 1,
"whole": 1,
"new": 1,
"future": 1,
"more": 1,
"information": 1,
"upc": 1,
"a34ba96d4081e6a4": 1,
"type": 1,
"price": 2,
"excl": 1,
"tax": 3,
"incl": 1,
"0": 2,
"00": 1,
"availability": 1,
"number": 1,
"reviews": 1,
"products": 1,
"you": 1,
"recently": 1,
"viewed": 1,
"scott": 1,
"pilgrim": 1,
"precious": 1,
"little": 1,
"52": 2,
"29": 1,
"add": 6,
"basket": 6,
"set": 1,
"me": 1,
"free": 1,
"17": 1,
"46": 1,
"shakespeare": 1,
"sonnets": 1,
"20": 1,
"66": 1,
"starving": 1,
"hearts": 1,
"triangular": 1,
"trade": 1,
"13": 1,
"99": 1,
"black": 1,
"maria": 1,
"15": 1,
"boys": 1,
"22": 1,
"60": 1
}